mtools/__init__.py
m_toolz-0.1.dist-info/METADATA
m_toolz-0.1.dist-info/WHEEL
m_toolz-0.1.dist-info/top_level.txt
m_toolz-0.1.dist-info/RECORD
