Metadata-Version: 2.1
Name: m-toolz
Version: 0.1
Summary: The best tools in the world
Home-page: http://github.com/matyifkbt/mtools
Author: MatyiFKBT
Author-email: mmatyi1999@gmail.com
License: MIT
Platform: UNKNOWN
